lusid_workflow/__init__.py
lusid_workflow/__version__.py
lusid_workflow/api_client.py
lusid_workflow/configuration.py
lusid_workflow/exceptions.py
lusid_workflow/rest.py
lusid_workflow/api/__init__.py
lusid_workflow/api/action_logs_api.py
lusid_workflow/api/application_metadata_api.py
lusid_workflow/api/event_handlers_api.py
lusid_workflow/api/task_definitions_api.py
lusid_workflow/api/tasks_api.py
lusid_workflow/api/workers_api.py
lusid_workflow/models/__init__.py
lusid_workflow/models/access_controlled_action.py
lusid_workflow/models/access_controlled_resource.py
lusid_workflow/models/action_definition.py
lusid_workflow/models/action_definition_response.py
lusid_workflow/models/action_details.py
lusid_workflow/models/action_details_response.py
lusid_workflow/models/action_id.py
lusid_workflow/models/action_log.py
lusid_workflow/models/action_log_item.py
lusid_workflow/models/action_log_origin.py
lusid_workflow/models/change_item.py
lusid_workflow/models/create_child_task_configuration.py
lusid_workflow/models/create_child_tasks_action.py
lusid_workflow/models/create_child_tasks_action_response.py
lusid_workflow/models/create_event_handler_request.py
lusid_workflow/models/create_new_task_activity.py
lusid_workflow/models/create_new_task_activity_response.py
lusid_workflow/models/create_task_definition_request.py
lusid_workflow/models/create_task_request.py
lusid_workflow/models/create_worker_request.py
lusid_workflow/models/deleted_entity_response.py
lusid_workflow/models/event_handler.py
lusid_workflow/models/event_handler_mapping.py
lusid_workflow/models/event_matching_pattern.py
lusid_workflow/models/fail.py
lusid_workflow/models/fail_response.py
lusid_workflow/models/field_mapping.py
lusid_workflow/models/get_worker_result_response.py
lusid_workflow/models/health_check.py
lusid_workflow/models/health_check_response.py
lusid_workflow/models/id_selector_definition.py
lusid_workflow/models/identifier_part_schema.py
lusid_workflow/models/initial_state.py
lusid_workflow_sdk_preview-0.1.1298.dist-info/METADATA
lusid_workflow_sdk_preview-0.1.1298.dist-info/WHEEL
lusid_workflow_sdk_preview-0.1.1298.dist-info/top_level.txt
lusid_workflow_sdk_preview-0.1.1298.dist-info/RECORD
